MANIFEST.in
README.md
setup.py
second_hand_songs_wrapper/VERSION
second_hand_songs_wrapper/__init__.py
second_hand_songs_wrapper/second_hand_songs_wrapper.py
second_hand_songs_wrapper.egg-info/PKG-INFO
second_hand_songs_wrapper.egg-info/SOURCES.txt
second_hand_songs_wrapper.egg-info/dependency_links.txt
second_hand_songs_wrapper.egg-info/entry_points.txt
second_hand_songs_wrapper.egg-info/requires.txt
second_hand_songs_wrapper.egg-info/top_level.txt
second_hand_songs_wrapper.egg-info/zip-safe
second_hand_songs_wrapper/test/__init__.py
second_hand_songs_wrapper/test/test_shs.py