Metadata-Version: 1.1
Name: second-hand-songs-wrapper
Version: 0.2.3
Summary: An API wrapper for second hand song db
Home-page: http://crouchofthewildtiger.com/
Author: Roman A. Taycher
Author-email: rtaycher1987@gmail.com
License: MIT License
Keywords: second hand songs,api wrapper,song covers,music
Platform: UNKNOWN
Classifier: Development Status :: 3 - Alpha
Classifier: Environment :: Console
Classifier: Intended Audience :: Developers
Classifier: License :: OSI Approved :: MIT License
Classifier: Operating System :: OS Independent
Classifier: Topic :: Internet
Classifier: Topic :: Internet :: WWW/HTTP :: Dynamic Content
Classifier: Topic :: Multimedia
Classifier: Topic :: Software Development :: Libraries :: Python Modules
